openfoamparser/__init__.py
openfoamparser/field_parser.py
openfoamparser/mesh_parser.py
openfoamparser/utils.py
openfoamparser_ilya-0.16.dist-info/licenses/LICENSE
openfoamparser_ilya-0.16.dist-info/METADATA
openfoamparser_ilya-0.16.dist-info/WHEEL
openfoamparser_ilya-0.16.dist-info/top_level.txt
openfoamparser_ilya-0.16.dist-info/RECORD
