Metadata-Version: 2.4
Name: openfoamparser_ilya
Version: 0.16
Summary: Lightweight library to parse OpenFOAM files using Numpy (Ofpp Fork)
Home-page: https://www.ccs-labs.org/
Author: CCS-Labs
Author-email: ilyarozhkov010@gmail.com
Project-URL: Parent Project Description, https://www.forschung-it-sicherheit-kommunikationssysteme.de/projekte/mamoko
Project-URL: Source, https://github.com/resi2311/openfoamparser.git
Project-URL: Forked from, https://github.com/ApolloLV/openfoamparser
Keywords: openfoam cfd parser
Classifier: Development Status :: 4 - Beta
Classifier: Intended Audience :: Science/Research
Classifier: Topic :: Scientific/Engineering
Classifier: License :: OSI Approved :: MIT License
Classifier: Programming Language :: Python :: 3
Classifier: Programming Language :: Python :: 3.7
Requires-Python: >=3.7
License-File: LICENSE
Requires-Dist: numpy
Dynamic: author
Dynamic: author-email
Dynamic: classifier
Dynamic: description
Dynamic: description-content-type
Dynamic: home-page
Dynamic: keywords
Dynamic: license-file
Dynamic: project-url
Dynamic: requires-dist
Dynamic: requires-python
Dynamic: summary
